workflowSession/__init__.py
workflowSession/workflow_details.py
workflowSession-4.1.2.dist-info/METADATA
workflowSession-4.1.2.dist-info/WHEEL
workflowSession-4.1.2.dist-info/top_level.txt
workflowSession-4.1.2.dist-info/RECORD
